strenglib/__init__.py
strenglib/codes/__init__.py
strenglib/codes/eurocodes/__init__.py
strenglib/codes/eurocodes/ec2/__init__.py
strenglib/codes/eurocodes/ec2/raw/__init__.py
strenglib/codes/eurocodes/ec2/raw/ch3/__init__.py
strenglib/codes/eurocodes/ec2/raw/ch3/concrete/__init__.py
strenglib/codes/eurocodes/ec2/raw/ch3/concrete/elastic_deformation.py
strenglib/codes/eurocodes/ec2/raw/ch3/concrete/strength.py
strenglib/codes/eurocodes/ec2/raw/ch3/concrete/stress_strain.py
strenglib/codes/eurocodes/ec2/raw/ch4/__init__.py
strenglib/codes/eurocodes/ec2/raw/ch4/concrete_cover.py
strenglib/codes/eurocodes/ec2/raw/ch5/__init__.py
strenglib/codes/eurocodes/ec2/raw/ch5/geometric_data/__init__.py
strenglib/codes/eurocodes/ec2/raw/ch5/geometric_data/effective_width.py
strenglib/codes/eurocodes/ec2/raw/ch6/__init__.py
strenglib/codes/eurocodes/ec2/raw/ch6/shear.py
strenglib/codes/eurocodes/ec8/__init__.py
strenglib/codes/eurocodes/ec8/cls/__init__.py
strenglib/codes/eurocodes/ec8/cls/seismic_action/__init__.py
strenglib/codes/eurocodes/ec8/cls/seismic_action/spectra.py
strenglib/codes/eurocodes/ec8/raw/__init__.py
strenglib/codes/eurocodes/ec8/raw/ch3/__init__.py
strenglib/codes/eurocodes/ec8/raw/ch3/seismic_action/__init__.py
strenglib/codes/eurocodes/ec8/raw/ch3/seismic_action/spectra.py
strenglib/codes/eurocodes/ec8/raw/ch5/__init__.py
strenglib/codes/eurocodes/ec8/raw/ch5/detailing/__init__.py
strenglib/codes/eurocodes/ec8/raw/ch5/detailing/beams.py
strenglib/codes/eurocodes/ec8/seismic_action/__init__.py
strenglib/codes/eurocodes/ec8/seismic_action/spectra.py
strenglib/codes/greek/__init__.py
strenglib/codes/greek/eak2000/__init__.py
strenglib/codes/greek/ekos2000/__init__.py
strenglib/codes/greek/kanepe/__init__.py
strenglib/codes/greek/kanepe/assessment/__init__.py
strenglib/codes/greek/kanepe/assessment/section_properties/__init__.py
strenglib/codes/greek/kanepe/assessment/section_properties/yield_point_rect.py
strenglib/codes/greek/kanepe/raw/__init__.py
strenglib-0.0.10.dist-info/LICENSE
strenglib-0.0.10.dist-info/METADATA
strenglib-0.0.10.dist-info/WHEEL
strenglib-0.0.10.dist-info/top_level.txt
strenglib-0.0.10.dist-info/RECORD
