Metadata-Version: 2.1
Name: strenglib
Version: 0.0.10
Summary: structural engineering library
Home-page: UNKNOWN
Author: panagop
Author-email: giorgos@panagop.com
License: UNKNOWN
Platform: UNKNOWN
Classifier: Programming Language :: Python :: 3.6
Classifier: License :: OSI Approved :: MIT License
Classifier: Operating System :: OS Independent
Requires-Dist: dataclasses
Requires-Dist: tabulate
